linkedin_extractor.py
linkedin_extractor-0.1.7.dist-info/licenses/LICENSE
linkedin_extractor-0.1.7.dist-info/METADATA
linkedin_extractor-0.1.7.dist-info/WHEEL
linkedin_extractor-0.1.7.dist-info/entry_points.txt
linkedin_extractor-0.1.7.dist-info/top_level.txt
linkedin_extractor-0.1.7.dist-info/RECORD
