Metadata-Version: 2.4
Name: linkedin-extractor
Version: 0.1.7
Summary: A LinkedIn data extraction toolkit for scraping skills, experience and more.
Author: Kristian Julsgaard, Kristian Nyborg Jespersen
License-Expression: MIT
Requires-Python: >=3.8
License-File: LICENSE
Requires-Dist: selenium>=4.0.0
Requires-Dist: beautifulsoup4>=4.9.0
Requires-Dist: webdriver-manager>=3.8.0
Dynamic: license-file
